monocleaner/__init__.py
monocleaner/hardrules.py
monocleaner/lm.py
monocleaner/monocleaner.py
monocleaner/monocleaner_train.py
monocleaner/normalize.py
monocleaner/tokenizer.py
monocleaner/util.py
monocleaner-1.7.1.data/scripts/monocleaner-download
monocleaner-1.7.1.dist-info/LICENSE
monocleaner-1.7.1.dist-info/METADATA
monocleaner-1.7.1.dist-info/WHEEL
monocleaner-1.7.1.dist-info/entry_points.txt
monocleaner-1.7.1.dist-info/top_level.txt
monocleaner-1.7.1.dist-info/RECORD
