Metadata-Version: 2.1
Name: monocleaner
Version: 1.7.1
Summary: Monolingual corpus fluency filter
Author-email: Prompsit Language Engineering <info@prompsit.com>
Maintainer-email: Jaume Zaragoza <jzaragoza@prompsit.com>
License: GNU General Public License v3.0
Project-URL: Homepage, https://github.com/bitextor/monocleaner
Project-URL: Monocleaner on GitHub, https://github.com/bitextor/monocleaner
Project-URL: Prompsit Language Engineering, http://www.prompsit.com
Project-URL: Macocu, https://macocu.eu/
Classifier: Environment :: Console
Classifier: Intended Audience :: Science/Research
Classifier: Programming Language :: Python :: 3.8
Classifier: License :: OSI Approved :: GNU General Public License v3 (GPLv3)
Classifier: Operating System :: POSIX :: Linux
Classifier: Topic :: Scientific/Engineering :: Artificial Intelligence
Classifier: Topic :: Text Processing :: Linguistic
Classifier: Topic :: Software Development :: Libraries :: Python Modules
Classifier: Topic :: Text Processing :: Filters
Requires-Python: >=3.8
License-File: LICENSE
Requires-Dist: regex
Requires-Dist: toolwrapper
Requires-Dist: sacremoses
Requires-Dist: numpy
Requires-Dist: pyyaml
Requires-Dist: fastspell==0.12
